{
  "categories": [
    {
      "id": 1,
      "name": "Men",
      "code": "MEN",
      "path": "/men",
      "description": "Men's Clothing",
      "types": [
        {
          "id": 1,
          "name": "Jeans",
          "description": "Men's jeans"
        },
        {
          "id": 2,
          "name": "Shirts",
          "description": "Men's shirts"
        },
        {
          "id": 3,
          "name": "Shorts",
          "description": "Men's shorts"
        },
        {
          "id": 4,
          "name": "T-shirts",
          "description": "Men's t-shirts"
        },
        {
          "id": 54,
          "name": "Hoodie's",
          "description": "Men's Hoodie"
        }
      ],
      "meta_data": {
        "colors": [
          "Black",
          "White",
          "Purple",
          "Gray",
          "Blue",
          "Red",
          "Orange",
          "Navy",
          "Grey",
          "Yellow",
          "Pink",
          "Green"
        ],
        "sizes": ["S", "M", "L", "XL", "XXL"]
      }
    },
    {
      "id": 2,
      "name": "Women",
      "code": "WOMEN",
      "path": "/women",
      "description": "Women's Clothing",
      "types": [
        {
          "id": 1,
          "code": "DRESSES",
          "name": "Dresses"
        },
        {
          "id": 2,
          "code": "CROPTOP",
          "name": "Crop Top"
        },
        {
          "id": 3,
          "code": "SHORTS",
          "name": "Shorts"
        },
        {
          "id": 4,
          "code": "JEANS",
          "name": "Jeans"
        },
        {
          "id": 5,
          "code": "TSHIRTS",
          "name": "T-shirt"
        },
        {
          "id": 6,
          "code": "SWEATSHIRT",
          "name": "Hoodie/Sweatshirt"
        },
        {
          "id": 7,
          "code": "TOPS",
          "name": "Tops"
        },
        {
          "id": 8,
          "code": "BOXERS",
          "name": "Boxers"
        },
        {
          "id": 9,
          "code": "KURTIS",
          "name": "Kurtis"
        }
      ],
      "meta_data": {
        "colors": [
          "Black",
          "White",
          "Purple",
          "Gray",
          "Blue",
          "Red",
          "Orange",
          "Navy",
          "Grey",
          "Yellow",
          "Pink",
          "Green"
        ],
        "sizes": ["S", "M", "L", "XL", "XXL"]
      }
    },
    {
      "id": 3,
      "name": "Kids",
      "code": "KIDS",
      "path": "/kids",
      "description": "Kid's Clothing",
      "types": [
        {
          "id": 1,
          "name": "T-shirts",
          "description": "Kids' t-shirts"
        },
        {
          "id": 12,
          "name": "Shorts",
          "description": "Kids' shorts"
        },
        {
          "id": 13,
          "name": "Dresses",
          "description": "Kids' dresses"
        },
        {
          "id": 14,
          "name": "Jeans",
          "description": "Kids' jeans"
        }
      ],
      "meta_data": {
        "colors": [
          "Black",
          "White",
          "Purple",
          "Gray",
          "Blue",
          "Red",
          "Orange",
          "Navy",
          "Grey",
          "Yellow",
          "Pink",
          "Green"
        ],
        "sizes": ["S"]
      }
    }
  ]
}
